vg_hubert/__init__.py
vg_hubert/mincut.py
vg_hubert/segmenter.py
vg_hubert/datasets/__init__.py
vg_hubert/datasets/places_dataset.py
vg_hubert/datasets/sampler.py
vg_hubert/datasets/spokencoco_dataset.py
vg_hubert/model/__init__.py
vg_hubert/model/audio_encoder.py
vg_hubert/model/dual_encoder.py
vg_hubert/model/utils.py
vg_hubert/model/vision_transformer.py
vg_hubert/model/vit_utils.py
vg_hubert/tests/test_better_params.py
vg_hubert/tests/test_hf_upload.py
vg_hubert/tests/test_mincut_comparison.py
vg_hubert/tests/test_mincut_quality.py
vg_hubert/training/__init__.py
vg_hubert/training/bert_adam.py
vg_hubert/training/trainer.py
vg_hubert/training/trainer_utils.py
vg_hubert/training/utils.py
vg_hubert-1.0.0.dist-info/licenses/LICENSE
vg_hubert-1.0.0.dist-info/METADATA
vg_hubert-1.0.0.dist-info/WHEEL
vg_hubert-1.0.0.dist-info/top_level.txt
vg_hubert-1.0.0.dist-info/RECORD
