Metadata-Version: 2.4
Name: vg-hubert
Version: 1.0.0
Summary: VG-HuBERT: Simplified interface for speech segmentation with HuggingFace Hub integration
Home-page: https://github.com/human-ai-lab/VG-HuBERT
Author: Puyuan Peng, David Harwath
Author-email: Puyuan Peng <harwath@utexas.edu>, David Harwath <harwath@utexas.edu>
License: BSD-3-Clause
Project-URL: Homepage, https://github.com/human-ai-lab/VG-HuBERT
Project-URL: Original Paper (Words), https://arxiv.org/abs/2203.15081
Project-URL: Original Paper (Syllables), https://www.isca-speech.org/archive/interspeech_2023/peng23_interspeech.html
Project-URL: HuggingFace Model, https://huggingface.co/hjvm/VG-HuBERT
Project-URL: Bug Tracker, https://github.com/human-ai-lab/VG-HuBERT/issues
Keywords: speech,audio,segmentation,syllables,self-supervised,hubert,vg-hubert
Classifier: Development Status :: 4 - Beta
Classifier: Intended Audience :: Science/Research
Classifier: License :: OSI Approved :: BSD License
Classifier: Programming Language :: Python :: 3
Classifier: Programming Language :: Python :: 3.8
Classifier: Programming Language :: Python :: 3.9
Classifier: Programming Language :: Python :: 3.10
Classifier: Programming Language :: Python :: 3.11
Classifier: Topic :: Scientific/Engineering :: Artificial Intelligence
Classifier: Topic :: Multimedia :: Sound/Audio :: Speech
Requires-Python: >=3.8
License-File: LICENSE
Requires-Dist: torch>=2.0.0
Requires-Dist: transformers>=4.20.0
Requires-Dist: huggingface-hub>=0.10.0
Requires-Dist: numpy>=1.20.0
Requires-Dist: soundfile>=0.10.0
Requires-Dist: scipy>=1.6.0
Provides-Extra: dev
Requires-Dist: pytest>=7.0.0; extra == "dev"
Requires-Dist: black>=22.0.0; extra == "dev"
Requires-Dist: isort>=5.10.0; extra == "dev"
Requires-Dist: flake8>=4.0.0; extra == "dev"
Dynamic: author
Dynamic: home-page
Dynamic: license-file
Dynamic: requires-python
